hra_jupyter_widgets/__init__.py
hra_jupyter_widgets/static/hra_app.js
hra_jupyter_widgets/static/model_viewer.css
hra_jupyter_widgets/static/model_viewer.js
hra_jupyter_widgets/trait_types/__init__.py
hra_jupyter_widgets/trait_types/attribute.py
hra_jupyter_widgets/trait_types/defs.py
hra_jupyter_widgets/trait_types/event.py
hra_jupyter_widgets/widgets/__init__.py
hra_jupyter_widgets/widgets/_stylesheets.py
hra_jupyter_widgets/widgets/body_ui.py
hra_jupyter_widgets/widgets/cde_visualization.py
hra_jupyter_widgets/widgets/eui.py
hra_jupyter_widgets/widgets/eui_organ_information.py
hra_jupyter_widgets/widgets/ftu_explorer.py
hra_jupyter_widgets/widgets/ftu_explorer_small.py
hra_jupyter_widgets/widgets/hra_app.py
hra_jupyter_widgets/widgets/medical_illustration.py
hra_jupyter_widgets/widgets/model_viewer.py
hra_jupyter_widgets/widgets/node_dist_vis.py
hra_jupyter_widgets/widgets/rui.py
hra_jupyter_widgets-0.4.1.dist-info/METADATA
hra_jupyter_widgets-0.4.1.dist-info/WHEEL
hra_jupyter_widgets-0.4.1.dist-info/licenses/LICENSE
hra_jupyter_widgets-0.4.1.dist-info/RECORD
