Metadata-Version: 2.4
Name: hra_jupyter_widgets
Version: 0.4.1
Project-URL: Homepage, https://github.com/x-atlas-consortia/hra-jupyter-widgets
Project-URL: Documentation, https://github.com/x-atlas-consortia/hra-jupyter-widgets
Project-URL: Repository, https://github.com/x-atlas-consortia/hra-jupyter-widgets.git
Project-URL: Issues, https://github.com/x-atlas-consortia/hra-jupyter-widgets/issues
Project-URL: Changelog, https://github.com/x-atlas-consortia/hra-jupyter-widgets/blob/main/CHANGELOG.md
Author-email: "Axel (Daniel) Bolin" <axbolin@iu.edu>, "Bruce W. Herr II" <bherr@iu.edu>
License-Expression: MIT
License-File: LICENSE
Keywords: HRA,Human Reference Atlas,jupyter,widgets
Requires-Python: >=3.9
Requires-Dist: anywidget
Requires-Dist: traitlets>=5.10
Provides-Extra: dev
Requires-Dist: jupyterlab; extra == 'dev'
Requires-Dist: watchfiles; extra == 'dev'
